docbuilder/__init__.py
docbuilder/docbuilder.py
docbuilder/lib/DoctRenderer.config
docbuilder/lib/cmap.bin
docbuilder/lib/docbuilder
docbuilder/lib/icudtl.dat
docbuilder/lib/icudtl_extra.dat
docbuilder/lib/libDjVuFile.so
docbuilder/lib/libDocxRenderer.so
docbuilder/lib/libEpubFile.so
docbuilder/lib/libFb2File.so
docbuilder/lib/libHWPFile.so
docbuilder/lib/libHtmlFile2.so
docbuilder/lib/libIWorkFile.so
docbuilder/lib/libOFDFile.so
docbuilder/lib/libPdfFile.so
docbuilder/lib/libUnicodeConverter.so
docbuilder/lib/libXpsFile.so
docbuilder/lib/libdocbuilder.c.so
docbuilder/lib/libdoctrenderer.so
docbuilder/lib/libgraphics.so
docbuilder/lib/libicudata.so.74
docbuilder/lib/libicuuc.so.74
docbuilder/lib/libkernel.so
docbuilder/lib/libkernel_network.so
docbuilder/lib/x2t
docbuilder/lib/dictionaries/README.md
docbuilder/lib/dictionaries/bg_BG/README_hyph_bg_BG.txt
docbuilder/lib/dictionaries/bg_BG/hyph_bg_BG.dic
docbuilder/lib/dictionaries/ca_ES/README_hyph_ca_ES.txt
docbuilder/lib/dictionaries/ca_ES/hyph_ca_ES.dic
docbuilder/lib/dictionaries/cs_CZ/hyph_cs_CZ.dic
docbuilder/lib/dictionaries/da_DK/README_hyph_da_DK.txt
docbuilder/lib/dictionaries/da_DK/hyph_da_DK.dic
docbuilder/lib/dictionaries/de_AT/hyph_de_AT.dic
docbuilder/lib/dictionaries/de_CH/hyph_de_CH.dic
docbuilder/lib/dictionaries/de_DE/README_hyph_de.txt
docbuilder/lib/dictionaries/de_DE/hyph_de_DE.dic
docbuilder/lib/dictionaries/el_GR/README_hyph_el_GR.txt
docbuilder/lib/dictionaries/el_GR/hyph_el_GR.dic
docbuilder/lib/dictionaries/en_AU/hyph_en_AU.dic
docbuilder/lib/dictionaries/en_GB/hyph_en_GB.dic
docbuilder/lib/dictionaries/en_US/README_hyph_en_US.txt
docbuilder/lib/dictionaries/en_US/hyph_en_US.dic
docbuilder/lib/dictionaries/es_ES/README_hyph_es_ES.txt
docbuilder/lib/dictionaries/es_ES/hyph_es_ES.dic
docbuilder/lib/dictionaries/fr_FR/README_hyph_fr_FR.txt
docbuilder/lib/dictionaries/fr_FR/hyph_fr_FR.dic
docbuilder/lib/dictionaries/gl_ES/README_hyph_gl_ES.txt
docbuilder/lib/dictionaries/gl_ES/hyph_gl_ES.dic
document_builder-9.2.1.43.dist-info/licenses/LICENSE
document_builder-9.2.1.43.dist-info/METADATA
document_builder-9.2.1.43.dist-info/WHEEL
document_builder-9.2.1.43.dist-info/top_level.txt
document_builder-9.2.1.43.dist-info/RECORD
