Metadata-Version: 2.4
Name: document-builder
Version: 9.2.1.43
Summary: Convenient Python wrapper for C++ Document Builder library
Home-page: https://github.com/ONLYOFFICE/core
Author: ONLYOFFICE
Author-email: support@onlyoffice.com
License: GNU Affero General Public License v3.0
Classifier: Programming Language :: Python :: 2.7
Classifier: Programming Language :: Python :: 3
Classifier: License :: OSI Approved :: GNU Affero General Public License v3
Classifier: Operating System :: MacOS
Classifier: Operating System :: MacOS :: MacOS X
Classifier: Operating System :: Microsoft :: Windows
Classifier: Operating System :: POSIX :: Linux
Classifier: Operating System :: Unix
Requires-Python: >=2.7
License-File: LICENSE
Dynamic: author
Dynamic: author-email
Dynamic: classifier
Dynamic: home-page
Dynamic: license
Dynamic: license-file
Dynamic: requires-python
Dynamic: summary
